mpitb/__init__.py
mpitb/core.py
mpitb/utils.py
mpitb-0.2.dist-info/licenses/LICENSE.md
mpitb-0.2.dist-info/METADATA
mpitb-0.2.dist-info/WHEEL
mpitb-0.2.dist-info/top_level.txt
mpitb-0.2.dist-info/RECORD
