Metadata-Version: 2.4
Name: mpitb
Version: 0.2
Summary: A toolbox for multidimensional poverty index (MPI) estimation and analysis
Author: Joseph Lam
Requires-Python: >=3.7
License-File: LICENSE.md
Requires-Dist: pandas
Requires-Dist: numpy
Requires-Dist: scipy
Dynamic: author
Dynamic: description
Dynamic: description-content-type
Dynamic: license-file
Dynamic: requires-dist
Dynamic: requires-python
Dynamic: summary
